Metadata-Version: 1.1
Name: uestcct
Version: 0.0.1
Summary: export uestc course table to google calendar
Home-page: https://github.com/helloqiu/uestc_course_table
Author: helloqiu
Author-email: helloqiu95@gmail.com
License: GPLv3
Platform: UNKNOWN
Classifier: Development Status :: 1 - Planning
Classifier: Environment :: Console
Classifier: Operating System :: MacOS
Classifier: Operating System :: POSIX
Classifier: Operating System :: POSIX :: Linux
Classifier: Operating System :: Microsoft :: Windows
Classifier: Programming Language :: Python :: 3 :: Only
